tap_messagebird/__init__.py
tap_messagebird/client.py
tap_messagebird/schemas/conversation.json
tap_messagebird/schemas/conversation_message.json
tap_messagebird/schemas/message.json
tap_messagebird/streams.py
tap_messagebird/tap.py
tap_messagebird-0.0.10.dist-info/LICENSE
tap_messagebird-0.0.10.dist-info/METADATA
tap_messagebird-0.0.10.dist-info/WHEEL
tap_messagebird-0.0.10.dist-info/entry_points.txt
tap_messagebird-0.0.10.dist-info/RECORD
