Metadata-Version: 2.1
Name: tap-messagebird
Version: 0.0.10
Summary: `tap-messagebird` is a Singer tap for Messagebird, built with the Meltano Singer SDK.
License: Apache 2.0
Keywords: ELT,Messagebird
Author: Meltano Team
Author-email: hello@meltano.com
Requires-Python: >=3.7.1,<3.11
Classifier: License :: Other/Proprietary License
Classifier: Programming Language :: Python :: 3
Classifier: Programming Language :: Python :: 3.8
Classifier: Programming Language :: Python :: 3.9
Classifier: Programming Language :: Python :: 3.10
Provides-Extra: s3
Requires-Dist: fs-s3fs (>=1.1.1,<2.0.0) ; extra == "s3"
Requires-Dist: requests (>=2.25.1,<3.0.0)
Requires-Dist: singer-sdk (>=0.24,<0.30)
